{
  "project_info": {
    "project_number": "986736235941",
    "project_id": "expense-tracker-app-b5cf4",
    "storage_bucket": "expense-tracker-app-b5cf4.firebasestorage.app"
  },
  "client": [
    {
      "client_info": {
        "mobilesdk_app_id": "1:986736235941:android:6f64c04ecb06da27c0444c",
        "android_client_info": {
          "package_name": "com.example.expense_tracker_app"
        }
      },
      "oauth_client": [],
      "api_key": [
        {
          "current_key": "AIzaSyA4cUYYec_v0D8sNYmmTJ-ObmiYLEgZUp4"
        }
      ],
      "services": {
        "appinvite_service": {
          "other_platform_oauth_client": []
        }
      }
    }
  ],
  "configuration_version": "1"
}